{
  "$schema": "http://json-schema.org/draft-07/schema#",
  "title": "IPPC e-Phyto Multi-Model Schema (Normal/Reexport/Withdraw)",
  "type": "object",
  "properties": {
    "xc_document": {
      "type": "object",
      "properties": {
        "doc_name": { "type": ["string"] },
        "doc_type": { "type": ["string", "integer"] },
        "doc_id": { "type": ["string", "integer"] },
        "issue_party_name": { "type": ["string"] },
        "status_code": { "type": ["string", "integer"] },
        "issue_date": { "type": ["string"] },
        "reference_docs": {
          "type": ["array"],
          "items": {
            "type": "object",
            "properties": {
              "relation_type_code": { "type": ["string"] },
              "doc_id": { "type": ["string", "integer"] },
              "PdfObject": { 
                "type": ["string"],
                "contentEncoding": "base64",
                "contentMediaType": "application/pdf"
              },
              "filename": { "type": ["string"] }
            },
            "required": ["relation_type_code", "doc_id"]
          }
        },
        "signatory_authen": {
          "type": "object",
          "properties": {
            "provider_party": {
              "type": "object",
              "properties": {
                "name": { "type": ["string"] },
                "specfied_person_name": { "type": ["string"] }
              },
              "required": ["name", "specfied_person_name"]
            },
            "issue_location": { "type": ["string", "object"] },
            "include_clauses": {
              "type": "array",
              "items": {
                "type": "object",
                "properties": { "id": { "type": ["string", "integer"] } },
                "required": ["id"]
              }
            }
          },
          "required": ["provider_party", "issue_location", "include_clauses"]
        },
        "include_notes": { "type": ["array"] }
      },
      "required": ["doc_name", "doc_type", "doc_id", "issue_party_name", "status_code", "issue_date", "signatory_authen"],
      "oneOf": [
        {
          "description": "IPPC Normal Case",
          "properties": {
            "doc_type": { "enum": ["851", 851] },
            "status_code": { "enum": ["70", 70] }
          }
        },
        {
          "description": "IPPC Reexport Case",
          "properties": {
            "doc_type": { "enum": ["657", 657] },
            "status_code": { "enum": ["40", 40, "70", 70] }
          },
          "required": ["reference_docs"]
        },
        {
          "description": "IPPC Withdraw/Replacement Case",
          "properties": {
            "doc_type": { "enum": ["851", 851] },
            "status_code": { "enum": ["40", 40] }
          }
        }
      ]
    },
    "consignment": {
      "type": "object",
      "properties": {
        "export_country": {
          "type": "object",
          "properties": {
            "id": { "type": ["string"] },
            "name": { "type": ["string"] },
            "subordinary": {
              "type": ["object"],
              "properties": {
                "name": { "type": ["string"] },
                "hierachi_level": { "type": ["string", "integer"] }
              },
              "required": ["name", "hierachi_level"]
            }
          },
          "required": ["id", "name"]
        },
        "import_country": {
          "type": "object",
          "properties": { "id": { "type": ["string"] }, "name": { "type": ["string"] } },
          "required": ["id", "name"]
        },
        "consignor_party": {
          "type": "object",
          "properties": { "name": { "type": ["string"] }, "adress_line1": { "type": ["string"] } },
          "required": ["name", "adress_line1"]
        },
        "consignee_party": {
          "type": "object",
          "properties": { "name": { "type": ["string"] }, "adress_line1": { "type": ["string"] } },
          "required": ["name", "adress_line1"]
        },
        "unloading_baseport": {
          "type": "object",
          "properties": { "name": { "type": ["string"] } },
          "required": ["name"]
        },
        "examination_event": {
          "type": "object",
          "properties": { "occur_location_name": { "type": ["string"] } },
          "required": ["occur_location_name"]
        },
        "main_carriages": {
          "type": "array",
          "minItems": 1,
          "items": {
            "type": "object",
            "properties": { "mode_code": { "type": ["string", "integer"] } },
            "required": ["mode_code"]
          }
        }
      },
      "required": ["export_country", "import_country", "consignor_party", "consignee_party", "unloading_baseport", "examination_event", "main_carriages"]
    },
    "items": {
      "type": "array",
      "minItems": 1,
      "items": {
        "type": "object",
        "properties": {
          "descriptions": {
            "type": "array",
            "items": { "type": "object", "properties": { "name": { "type": ["string"] } }, "required": ["name"] }
          },
          "origin_countries": {
            "type": "array",
            "items": {
              "type": "object",
              "properties": { "id": { "type": ["string"] }, "name": { "type": ["string"] } },
              "required": ["id", "name"]
            }
          },
          "intend_uses": {
            "type": "array",
            "items": { "type": "object", "properties": { "name": { "type": ["string"] } }, "required": ["name"] }
          }
        },
        "required": ["descriptions", "origin_countries", "intend_uses"]
      }
    },
    "phytoCerts": {
      "type": "array",
      "items": {
        "type": "object",
        "properties": {
          "sequenceNo": { "type": ["integer", "string"] },
          "Name": { "type": "string" },
          "documentNo": { "type": "string" },
          "PdfObject": { 
            "type": "string",
            "contentEncoding": "base64",
            "contentMediaType": "application/pdf"
          }
        },
        "required": ["sequenceNo", "Name", "documentNo", "PdfObject"]
      }
    }
  },
  "required": ["xc_document", "consignment", "items", "phytoCerts"]
}
